custom_hovertip/__init__.py
custom_hovertip/tkinter_tooltip.py
Custom_Tooltip-1.3.dist-info/LICENSE
Custom_Tooltip-1.3.dist-info/METADATA
Custom_Tooltip-1.3.dist-info/WHEEL
Custom_Tooltip-1.3.dist-info/top_level.txt
Custom_Tooltip-1.3.dist-info/RECORD
